itemparser/__init__.py
itemparser/field.py
itemparser/parser.py
itemparser/processor.py
itemparser-0.2.4.dist-info/METADATA
itemparser-0.2.4.dist-info/WHEEL
itemparser-0.2.4.dist-info/RECORD
