Metadata-Version: 2.1
Name: itemparser
Version: 0.2.4
Summary: parser for item
Author: miclon
Author-email: jcnd@163.com
Requires-Python: >=3.8,<4.0
Classifier: Programming Language :: Python :: 3
Classifier: Programming Language :: Python :: 3.8
Classifier: Programming Language :: Python :: 3.9
Classifier: Programming Language :: Python :: 3.10
Classifier: Programming Language :: Python :: 3.11
Classifier: Programming Language :: Python :: 3.12
Requires-Dist: parsel (>=1.8.1,<2.0.0)
